aiojito/__init__.py
aiojito/api/__init__.py
aiojito/api/block_engine.py
aiojito/api/searcher.py
aiojito/api/tip_payment_account.py
aiojito/async_api/__init__.py
aiojito/async_api/searcher.py
aiojito-0.1.1.dist-info/METADATA
aiojito-0.1.1.dist-info/WHEEL
aiojito-0.1.1.dist-info/entry_points.txt
aiojito-0.1.1.dist-info/licenses/LICENSE
aiojito-0.1.1.dist-info/RECORD
