Metadata-Version: 2.4
Name: aiojito
Version: 0.1.1
Summary: An async Python library for interacting with the Jito JSON-RPC
Project-URL: Homepage, https://github.com/CyberPlayerOne/aiojito
Author-email: Tyler Tang <lonewar@outlook.com>
License: MIT
License-File: LICENSE
Requires-Python: >=3.10
Requires-Dist: aiohttp>=3.12.14
Requires-Dist: loguru>=0.7.3
Requires-Dist: requests>=2.32.4
